lemniscat/plugin/azurecli/__init__.py
lemniscat/plugin/azurecli/azurecli.py
lemniscat/plugin/azurecli/filestore.py
lemniscat/plugin/azurecli/main.py
lemniscat/plugin/azurecli/plugin.yaml
lemniscat/plugin/azurecli/requirements.txt
lemniscat.plugin.azurecli-0.3.0.dist-info/LICENSE
lemniscat.plugin.azurecli-0.3.0.dist-info/METADATA
lemniscat.plugin.azurecli-0.3.0.dist-info/WHEEL
lemniscat.plugin.azurecli-0.3.0.dist-info/top_level.txt
lemniscat.plugin.azurecli-0.3.0.dist-info/RECORD
